{
  "check_id": "scoring.fe_be_parity",
  "phase": "09",
  "grades": ["G2", "G3", "G4", "G5"],
  "status": "active",
  "producer": {
    "cmd_pattern": "^python .*measure_submission\\.py",
    "must_exit_zero": true
  },
  "provenance_required": ["fe_side_exists"],
  "applicability": "fe_side_exists == 1",
  "assertions": [
    {
      "expr": "parity_category == 'full' or parity_category == 'missing_one' or parity_category == 'missing_two' or parity_category == 'smoke_only'",
      "on_fail": "parity_category must be one of full/missing_one/missing_two/smoke_only (dual-side 전제 — applicability fe_side_exists==1 에서만 평가); 단일 사이드 기능은 producer 가 fe_side_exists=0 을 emit → meta_audit 이 NA(침묵리에 0.0 채점 안 함)"
    }
  ],
  "value": "(parity_category == 'full') * 1.0 + (parity_category == 'missing_one') * 0.7 + (parity_category == 'missing_two') * 0.4 + (parity_category == 'smoke_only') * 0.0",
  "absence_policy": "FAIL"
}
